showit/VERSION
showit/__init__.py
showit/showit.py
showit_again-1.1.4.dist-info/DESCRIPTION.rst
showit_again-1.1.4.dist-info/METADATA
showit_again-1.1.4.dist-info/RECORD
showit_again-1.1.4.dist-info/WHEEL
showit_again-1.1.4.dist-info/metadata.json
showit_again-1.1.4.dist-info/top_level.txt
